jtd_codebuild/__init__.py
jtd_codebuild/__main__.py
jtd_codebuild/bundler.py
jtd_codebuild/cli.py
jtd_codebuild/codebuild.py
jtd_codebuild/commands/__init__.py
jtd_codebuild/commands/_build.py
jtd_codebuild/commands/_command.py
jtd_codebuild/commands/_init.py
jtd_codebuild/component.py
jtd_codebuild/config/__init__.py
jtd_codebuild/config/project/__init__.py
jtd_codebuild/config/project/_project.py
jtd_codebuild/config/project/config.json
jtd_codebuild/config/project/model/__init__.py
jtd_codebuild/config/project/model/_config.py
jtd_codebuild/config/project/model/_target.py
jtd_codebuild/config/project/model/_types.py
jtd_codebuild/config/project/scripts/__init__.py
jtd_codebuild/config/project/scripts/generate_project_config_json_schema.py
jtd_codebuild/config/workspace/__init__.py
jtd_codebuild/config/workspace/_workspace.py
jtd_codebuild/generators/__init__.py
jtd_codebuild/generators/_generator.py
jtd_codebuild/generators/_values.py
jtd_codebuild/generators/csharp/__init__.py
jtd_codebuild/generators/csharp/_generator.py
jtd_codebuild/generators/go/__init__.py
jtd_codebuild/generators/go/_generator.py
jtd_codebuild/generators/java/__init__.py
jtd_codebuild/generators/java/_generator.py
jtd_codebuild/generators/python/__init__.py
jtd_codebuild/generators/python/_generator.py
jtd_codebuild/generators/ruby/__init__.py
jtd_codebuild/generators/ruby/_generator.py
jtd_codebuild/generators/rust/__init__.py
jtd_codebuild/generators/rust/_generator.py
jtd_codebuild/generators/typescript/__init__.py
jtd_codebuild/generators/typescript/_generator.py
jtd_codebuild/inheritance.py
jtd_codebuild/logger/__init__.py
jtd_codebuild/logger/_click_logger.py
jtd_codebuild/logger/_logger.py
jtd_codebuild/logger/_noop_logger.py
jtd_codebuild/preset/__init__.py
jtd_codebuild/preset/_preset.py
jtd_codebuild/preset/config/__init__.py
jtd_codebuild/preset/config/_preset.py
jtd_codebuild/preset/config/templates/jtd-codebuild.json
jtd_codebuild/preset/project/__init__.py
jtd_codebuild-1.0.1.dist-info/LICENSE
jtd_codebuild-1.0.1.dist-info/METADATA
jtd_codebuild-1.0.1.dist-info/WHEEL
jtd_codebuild-1.0.1.dist-info/entry_points.txt
jtd_codebuild-1.0.1.dist-info/RECORD
