Metadata-Version: 2.1
Name: jtd-codebuild
Version: 1.0.1
Summary: Tool for generating language specific schemas and interfaces code from JSON Type Definition IDL files in yaml format. Powered by jtd-codegen.
License: MIT
Author: 01Joseph-Hwang10
Author-email: joseph95501@gmail.com
Requires-Python: >=3.8.1,<4.0
Classifier: Development Status :: 5 - Production/Stable
Classifier: Intended Audience :: Developers
Classifier: License :: OSI Approved :: MIT License
Classifier: Natural Language :: English
Classifier: Programming Language :: Python :: 3
Classifier: Programming Language :: Python :: 3.9
Classifier: Programming Language :: Python :: 3.10
Classifier: Programming Language :: Python :: 3.11
Classifier: Programming Language :: Python :: 3.12
Classifier: Programming Language :: Python :: 3 :: Only
Classifier: Programming Language :: Python :: 3.13
Classifier: Programming Language :: Python :: 3.8
Classifier: Programming Language :: Python :: Implementation :: CPython
Classifier: Programming Language :: Python :: Implementation :: PyPy
Classifier: Topic :: Software Development
Classifier: Topic :: Software Development :: Libraries :: Python Modules
Classifier: Topic :: Utilities
Requires-Dist: case-converter (>=1.1.0,<2.0.0)
Requires-Dist: click (>=8.1.7,<9.0.0)
Requires-Dist: colorama (>=0.4.6,<0.5.0)
Requires-Dist: deepmerge (>=1.1.1,<2.0.0)
Requires-Dist: joblib (>=1.4.0,<2.0.0)
Requires-Dist: pydantic (>=2.7.1,<3.0.0)
Requires-Dist: pyyaml (>=6.0.1,<7.0.0)
Requires-Dist: toolz (>=0.12.1,<0.13.0)
